setup.py
arxiv_pdf/__init__.py
arxiv_pdf/func.py
arxiv_pdf.egg-info/PKG-INFO
arxiv_pdf.egg-info/SOURCES.txt
arxiv_pdf.egg-info/dependency_links.txt
arxiv_pdf.egg-info/requires.txt
arxiv_pdf.egg-info/top_level.txt