Metadata-Version: 1.0
Name: arxiv-pdf
Version: 0.0.2
Summary: download arxiv papers
Home-page: UNKNOWN
Author: Wanghaibo
Author-email: dasuda2015@163.com
License: MIT Licence
Keywords: pip,arxiv
Platform: any
